reportlabextras/__init__.py
reportlabextras/main.py
reportlabextras-0.2.dist-info/METADATA
reportlabextras-0.2.dist-info/WHEEL
reportlabextras-0.2.dist-info/top_level.txt
reportlabextras-0.2.dist-info/RECORD
