Metadata-Version: 2.1
Name: reportlabextras
Version: 0.2
Summary: Adds the ability to have inbuilt fractions and powers written within the PDF itself for mathematical purposes.
Author: Bohdan Paris
Classifier: Programming Language :: Python :: 3
Classifier: License :: OSI Approved :: MIT License
Classifier: Operating System :: OS Independent
Requires-Python: >=3.6
Requires-Dist: reportlab>=4.2.2
